unpy2exe.py
unpy2exe-0.4.data/scripts/unpy2exe
unpy2exe-0.4.dist-info/METADATA
unpy2exe-0.4.dist-info/RECORD
unpy2exe-0.4.dist-info/WHEEL
unpy2exe-0.4.dist-info/top_level.txt
