Metadata-Version: 2.1
Name: unpy2exe
Version: 0.4
Summary: Extract pyc files from py2exe executable.
Home-page: http://github.com/matiasb/unpy2exe
Author: Matias Bordese
Author-email: mbordese@gmail.com
License: MIT
Keywords: py2exe,pyc,extract
Platform: UNKNOWN
Classifier: Intended Audience :: Developers
Classifier: Development Status :: 4 - Beta
Classifier: Programming Language :: Python :: 2
Classifier: Programming Language :: Python :: 3
Requires-Dist: argparse
Requires-Dist: pefile
Requires-Dist: six
